cacheable_keras/__init__.py
cacheable_keras/cacheable.py
keras_grid_search_cacheable-1.0.0.dist-info/LICENSE
keras_grid_search_cacheable-1.0.0.dist-info/METADATA
keras_grid_search_cacheable-1.0.0.dist-info/WHEEL
keras_grid_search_cacheable-1.0.0.dist-info/top_level.txt
keras_grid_search_cacheable-1.0.0.dist-info/RECORD
