Metadata-Version: 2.1
Name: keras-grid-search-cacheable
Version: 1.0.0
Summary: Reducción de tiempo de ejecución de los algoritmos de Machine Learning con búsqueda de parámetros en GridSearch.
Home-page: https://github.com/machine-learning-tools/keras-grid-search-cacheable
Author: Daniel Espinosa
Author-email: daespinosag@unal.edu.co
License: UNKNOWN
Platform: UNKNOWN
Classifier: Programming Language :: Python :: 3
Classifier: License :: OSI Approved :: MIT License
Classifier: Operating System :: OS Independent
Requires-Python: >=3.6.9
Requires-Dist: tensorflow (>=1.15.0)
